freeipa_auth/__init__.py
freeipa_auth/backends.py
freeipa_auth/conftest.py
freeipa_auth/freeipa_utils.py
freeipa_auth/tests.py
django_freeipa_auth-0.1.dev6.dist-info/LICENSE
django_freeipa_auth-0.1.dev6.dist-info/METADATA
django_freeipa_auth-0.1.dev6.dist-info/WHEEL
django_freeipa_auth-0.1.dev6.dist-info/top_level.txt
django_freeipa_auth-0.1.dev6.dist-info/RECORD
