Metadata-Version: 2.1
Name: django-freeipa-auth
Version: 0.1.dev6
Summary: A simple django freeipa rpc authentication backend app with a simple server failover solution.
Home-page: UNKNOWN
Author: Jerry Aujla
Author-email: jerryaujla1@gmail.com
License: BSD License
Platform: UNKNOWN
Classifier: Environment :: Web Environment
Classifier: Framework :: Django
Classifier: Framework :: Django :: 1.9
Classifier: Intended Audience :: Developers
Classifier: License :: OSI Approved :: BSD License
Classifier: Operating System :: OS Independent
Classifier: Programming Language :: Python
Classifier: Programming Language :: Python :: 2
Classifier: Programming Language :: Python :: 2.7
Classifier: Topic :: Internet :: WWW/HTTP
Classifier: Topic :: Internet :: WWW/HTTP :: Dynamic Content
Requires-Dist: requests
Requires-Dist: Django (>=1.8.0)
Provides-Extra: security
Requires-Dist: pyOpenSSL (>=0.14); extra == 'security'
Requires-Dist: cryptography (>=1.3.4); extra == 'security'
Requires-Dist: idna (>=2.0.0); extra == 'security'
